mailgw_temporary_email/__init__.py
mailgw_temporary_email/email.py
mailgw_temporary_email/message.py
MailGw_Temporary_Email-0.0.2.dist-info/LICENSE
MailGw_Temporary_Email-0.0.2.dist-info/METADATA
MailGw_Temporary_Email-0.0.2.dist-info/WHEEL
MailGw_Temporary_Email-0.0.2.dist-info/top_level.txt
MailGw_Temporary_Email-0.0.2.dist-info/RECORD
