Metadata-Version: 2.1
Name: MailGw-Temporary-Email
Version: 0.0.2
Summary: 10 Minute Temporary Email
Home-page: https://github.com/bontoutou00/MailGw
Author: bontoutou
Project-URL: Bug Tracker, https://github.com/bontoutou00/MailGw/issues
Keywords: mail,email,temporary mail,temporary email,mailgw
Classifier: Programming Language :: Python :: 3
Classifier: License :: OSI Approved :: MIT License
Classifier: Operating System :: OS Independent
Requires-Python: >=3.6
License-File: LICENSE
Requires-Dist: requests
